build/lib/polycraft_lab/__init__.py
build/lib/polycraft_lab/__main__.py
build/lib/polycraft_lab/cli/__init__.py
build/lib/polycraft_lab/cli/entrypoint.py
build/lib/polycraft_lab/cli/wrapper.py
build/lib/polycraft_lab/ect/__init__.py
build/lib/polycraft_lab/ect/experiment_config.py
build/lib/polycraft_lab/envs/__init__.py
build/lib/polycraft_lab/envs/core.py
build/lib/polycraft_lab/envs/dynamic_environment.py
build/lib/polycraft_lab/envs/helpers.py
build/lib/polycraft_lab/examples/__init__.py
build/lib/polycraft_lab/examples/pogo_stick.py
build/lib/polycraft_lab/installation/__init__.py
build/lib/polycraft_lab/installation/client.py
build/lib/polycraft_lab/installation/config.py
build/lib/polycraft_lab/installation/download.py
build/lib/polycraft_lab/installation/manager.py
build/lib/polycraft_lab/installation/post_pip_install.py
build/lib/polycraft_lab/installation/releases.py
build/lib/polycraft_lab/tests/__init__.py
build/lib/polycraft_lab/tests/download_test.py
build/lib/polycraft_lab/tests/examples_tests.py
build/lib/polycraft_lab/turtle/__init__.py
build/lib/polycraft_lab/turtle/turtle.py
polycraft_lab/__init__.py
polycraft_lab/__main__.py
polycraft_lab/cli/__init__.py
polycraft_lab/cli/entrypoint.py
polycraft_lab/cli/wrapper.py
polycraft_lab/ect/__init__.py
polycraft_lab/ect/experiment_config.py
polycraft_lab/envs/__init__.py
polycraft_lab/envs/core.py
polycraft_lab/envs/dynamic_environment.py
polycraft_lab/envs/helpers.py
polycraft_lab/examples/__init__.py
polycraft_lab/examples/pogo_stick.py
polycraft_lab/installation/__init__.py
polycraft_lab/installation/client.py
polycraft_lab/installation/config.py
polycraft_lab/installation/download.py
polycraft_lab/installation/manager.py
polycraft_lab/installation/post_pip_install.py
polycraft_lab/installation/releases.py
polycraft_lab/tests/__init__.py
polycraft_lab/tests/download_test.py
polycraft_lab/tests/examples_tests.py
polycraft_lab/turtle/__init__.py
polycraft_lab/turtle/turtle.py
polycraft_lab-0.1.0a0.dist-info/LICENSE.md
polycraft_lab-0.1.0a0.dist-info/METADATA
polycraft_lab-0.1.0a0.dist-info/WHEEL
polycraft_lab-0.1.0a0.dist-info/entry_points.txt
polycraft_lab-0.1.0a0.dist-info/top_level.txt
polycraft_lab-0.1.0a0.dist-info/RECORD
