Metadata-Version: 2.1
Name: polycraft-lab
Version: 0.1.0a0
Summary: A tool to help train RL agents in novel environments.
Home-page: https://polycraftworld.com
Author: Polycraft World
Author-email: willie.chalmers@polycraftworld.com
License: UNKNOWN
Project-URL: Bug Tracker, https://github.com/PolycraftWorld/polycraft-ai-lab/issues/
Project-URL: Documentation, https://polycraftworld.github.io/polycraft-ai-lab/
Project-URL: Source Code, https://github.com/PolycraftWorld/polycraft-ai-lab/
Platform: UNKNOWN
Classifier: Programming Language :: Python :: 3
Classifier: Operating System :: OS Independent
Classifier: Development Status :: 3 - Alpha
Requires-Python: >=3.6
Requires-Dist: gym
Requires-Dist: requests
Requires-Dist: tqdm
Requires-Dist: fire
